MANIFEST.in
README.rst
requirements.txt
setup.py
emites_api/__init__.py
emites_api/main.py
emites_api/tests/__init__.py
emites_api/tests/helpers.py
emites_api/tests/main.py
emites_api/tests/cassettes/emites/collections_options
emites_api/tests/cassettes/emites/batches/cancel_empty_batch
emites_api/tests/cassettes/emites/batches/cancel_sent_batch
emites_api/tests/cassettes/emites/batches/create
emites_api/tests/cassettes/emites/batches/create_empty_batch
emites_api/tests/cassettes/emites/batches/create_without_emitter_id
emites_api/tests/cassettes/emites/batches/create_without_name
emites_api/tests/cassettes/emites/batches/filter_by_emitter
emites_api/tests/cassettes/emites/batches/filter_by_name
emites_api/tests/cassettes/emites/batches/filter_by_other_emitter
emites_api/tests/cassettes/emites/batches/filter_by_status
emites_api/tests/cassettes/emites/batches/get_from_another_account
emites_api/tests/cassettes/emites/batches/get_from_this_account
emites_api/tests/cassettes/emites/batches/history
emites_api/tests/cassettes/emites/batches/list
emites_api/tests/cassettes/emites/batches/send
emites_api/tests/cassettes/emites/batches/send_empty_batch
emites_api/tests/cassettes/emites/batches/nfse/create
emites_api/tests/cassettes/emites/batches/nfse/list
emites_api/tests/cassettes/emites/emitters/create
emites_api/tests/cassettes/emites/emitters/create_without_certificate
emites_api/tests/cassettes/emites/emitters/create_without_city
emites_api/tests/cassettes/emites/emitters/create_without_city_inscription
emites_api/tests/cassettes/emites/emitters/create_without_cnpj
emites_api/tests/cassettes/emites/emitters/create_without_email
emites_api/tests/cassettes/emites/emitters/create_without_fancy_name
emites_api/tests/cassettes/emites/emitters/create_without_neighborhood
emites_api/tests/cassettes/emites/emitters/create_without_number
emites_api/tests/cassettes/emites/emitters/create_without_password
emites_api/tests/cassettes/emites/emitters/create_without_phone
python_emites.egg-info/PKG-INFO
python_emites.egg-info/SOURCES.txt
python_emites.egg-info/dependency_links.txt
python_emites.egg-info/requires.txt
python_emites.egg-info/top_level.txt