Metadata-Version: 1.1
Name: python-emites
Version: 0.1.0
Summary: Python client app for Emites (api v1).
Home-page: http://github.com/myfreecomm/emites
Author: vitormazzi
Author-email: vitormazzi@gmail.com
License: Apache 2.0
Keywords: python emites
Platform: UNKNOWN
Classifier: Intended Audience :: Developers
Classifier: License :: OSI Approved :: Apache Software License
Classifier: Operating System :: OS Independent
Classifier: Topic :: Software Development
